admincolors/__init__.py
admincolors/apps.py
admincolors/context_processors.py
admincolors/site.py
admincolors/static/admincolors/css/dark-blue.css
admincolors/static/admincolors/css/default.css
admincolors/static/admincolors/css/gray.css
admincolors/static/admincolors/css/lite.css
admincolors/static/admincolors/js/theme.js
admincolors/templates/admincolors/base_site.html
admincolors/templates/admincolors/index.html
admincolors/templates/admincolors/templatetags/breadcrumbs.html
admincolors/templates/admincolors/templatetags/scripts.html
admincolors/templates/admincolors/templatetags/styles.html
admincolors/templatetags/__init__.py
admincolors/templatetags/admincolors.py
admincolors/tests/__init__.py
admincolors/tests/test_apps.py
admincolors/tests/test_context_processors.py
admincolors/tests/test_site.py
admincolors/tests/test_templatetags.py
admincolors/tests/app/__init__.py
admincolors/tests/app/settings.py
admincolors/tests/app/urls.py
admincolors/tests/app/wsgi.py
django_admin_colors-0.2.0.dist-info/DESCRIPTION.rst
django_admin_colors-0.2.0.dist-info/METADATA
django_admin_colors-0.2.0.dist-info/RECORD
django_admin_colors-0.2.0.dist-info/WHEEL
django_admin_colors-0.2.0.dist-info/metadata.json
django_admin_colors-0.2.0.dist-info/top_level.txt
