Metadata-Version: 1.1
Name: django-admin-colors
Version: 0.2.0
Summary: Customizable Django admin themes
Home-page: https://github.com/victorfsf/django-admin-colors
Author: Victor Ferraz
Author-email: victorfsf.dev@gmail.com
License: MIT License
Keywords: django,django-admin,python3,python3.6,colors,themes,django-admin-colors,django-admin-themes
Platform: UNKNOWN
Classifier: Environment :: Web Environment
Classifier: Framework :: Django
Classifier: Framework :: Django :: 2.0
Classifier: Intended Audience :: Developers
Classifier: License :: OSI Approved :: MIT License
Classifier: Operating System :: OS Independent
Classifier: Programming Language :: Python
Classifier: Programming Language :: Python :: 3.5
Classifier: Programming Language :: Python :: 3.6
Classifier: Topic :: Internet :: WWW/HTTP
Classifier: Topic :: Internet :: WWW/HTTP :: Dynamic Content
